path_diag-0.0.1.data/data/scripts/path-diag-functions.sh
path_diag-0.0.1.data/scripts/path-diag-functions.sh
path_diag-0.0.1.dist-info/METADATA
path_diag-0.0.1.dist-info/RECORD
path_diag-0.0.1.dist-info/WHEEL
path_diag-0.0.1.dist-info/entry_points.txt
path_diag-0.0.1.dist-info/top_level.txt
src/__init__.py
src/pathdiag.py
